MANIFEST.in
README.md
setup.py
ctcdecode/__init__.py
ctcdecode/src/binding.cpp
ctcdecode/src/ctc_beam_search_decoder.cpp
ctcdecode/src/decoder_utils.cpp
ctcdecode/src/path_trie.cpp
ctcdecode/src/scorer.cpp
ctcdecodeupd.egg-info/PKG-INFO
ctcdecodeupd.egg-info/SOURCES.txt
ctcdecodeupd.egg-info/dependency_links.txt
ctcdecodeupd.egg-info/top_level.txt
third_party/kenlm/lm/bhiksha.cc
third_party/kenlm/lm/binary_format.cc
third_party/kenlm/lm/config.cc
third_party/kenlm/lm/lm_exception.cc
third_party/kenlm/lm/model.cc
third_party/kenlm/lm/quantize.cc
third_party/kenlm/lm/read_arpa.cc
third_party/kenlm/lm/search_hashed.cc
third_party/kenlm/lm/search_trie.cc
third_party/kenlm/lm/sizes.cc
third_party/kenlm/lm/trie.cc
third_party/kenlm/lm/trie_sort.cc
third_party/kenlm/lm/value_build.cc
third_party/kenlm/lm/virtual_interface.cc
third_party/kenlm/lm/vocab.cc
third_party/kenlm/util/bit_packing.cc
third_party/kenlm/util/ersatz_progress.cc
third_party/kenlm/util/exception.cc
third_party/kenlm/util/file.cc
third_party/kenlm/util/file_piece.cc
third_party/kenlm/util/float_to_string.cc
third_party/kenlm/util/integer_to_string.cc
third_party/kenlm/util/mmap.cc
third_party/kenlm/util/murmur_hash.cc
third_party/kenlm/util/parallel_read.cc
third_party/kenlm/util/pool.cc
third_party/kenlm/util/read_compressed.cc
third_party/kenlm/util/scoped.cc
third_party/kenlm/util/spaces.cc
third_party/kenlm/util/string_piece.cc
third_party/kenlm/util/usage.cc
third_party/kenlm/util/double-conversion/bignum-dtoa.cc
third_party/kenlm/util/double-conversion/bignum.cc
third_party/kenlm/util/double-conversion/cached-powers.cc
third_party/kenlm/util/double-conversion/diy-fp.cc
third_party/kenlm/util/double-conversion/double-conversion.cc
third_party/kenlm/util/double-conversion/fast-dtoa.cc
third_party/kenlm/util/double-conversion/fixed-dtoa.cc
third_party/kenlm/util/double-conversion/strtod.cc
third_party/openfst-1.6.7/src/lib/compat.cc
third_party/openfst-1.6.7/src/lib/flags.cc
third_party/openfst-1.6.7/src/lib/fst-types.cc
third_party/openfst-1.6.7/src/lib/fst.cc
third_party/openfst-1.6.7/src/lib/mapped-file.cc
