Metadata-Version: 1.0
Name: ctcdecodeupd
Version: 1.0.5
Summary: CTC Decoder for PyTorch based on Paddle Paddle's implementation
Home-page: https://github.com/parlance/ctcdecode
Author: Ryan Leary
Author-email: ryanleary@gmail.com
License: UNKNOWN
Platform: UNKNOWN
